ldbg/__init__.py
ldbg/ldbg.py
ldbg/py.typed
ldbg-0.1.4.dist-info/METADATA
ldbg-0.1.4.dist-info/WHEEL
ldbg-0.1.4.dist-info/RECORD
