Metadata-Version: 2.4
Name: ldbg
Version: 0.1.4
Summary: Add your description here
Author-email: Arthur Masson <arthur.masson@inria.fr>
Requires-Python: >=3.10
Requires-Dist: openai>=1.107.3
